{
    "Ar36": {
        "error": 1.0615759505318316,
        "error_type": "",
        "fit": "previous",
        "references": [
            {
                "exclude": false,
                "record_id": "ba-02-N-110"
            }
        ],
        "value": 16.18674883627496
    },
    "Ar37": {
        "error": 2.5437175844661084,
        "error_type": "",
        "fit": "previous",
        "references": [
            {
                "exclude": false,
                "record_id": "ba-02-N-110"
            }
        ],
        "value": 76.56795182502367
    },
    "Ar38": {
        "error": 0.504607527894959,
        "error_type": "",
        "fit": "previous",
        "references": [
            {
                "exclude": false,
                "record_id": "ba-02-N-110"
            }
        ],
        "value": 2.7094837029122703
    },
    "Ar39": {
        "error": 0.6662494803279176,
        "error_type": "",
        "fit": "previous",
        "references": [
            {
                "exclude": false,
                "record_id": "ba-02-N-110"
            }
        ],
        "value": 19.8737639190297
    },
    "Ar40": {
        "error": 115.44548710837068,
        "error_type": "",
        "fit": "previous",
        "references": [
            {
                "exclude": false,
                "record_id": "ba-02-N-110"
            }
        ],
        "value": 4358.089590390031
    }
}