{
    "Ar36": {
        "error": 2.9851790832864165,
        "error_type": "",
        "fit": "previous",
        "references": [
            {
                "exclude": false,
                "record_id": "ba-01-N-4877"
            }
        ],
        "value": 802.807720985168
    },
    "Ar37": {
        "error": 2.0459228370109326e-06,
        "error_type": "",
        "fit": "previous",
        "references": [
            {
                "exclude": false,
                "record_id": "ba-01-N-4877"
            }
        ],
        "value": 1.7092435396167594e-05
    },
    "Ar38": {
        "error": 3.397166467485655e-07,
        "error_type": "",
        "fit": "previous",
        "references": [
            {
                "exclude": false,
                "record_id": "ba-01-N-4877"
            }
        ],
        "value": 4.7260426853908726e-06
    },
    "Ar39": {
        "error": 1.6533727973054666e-06,
        "error_type": "",
        "fit": "previous",
        "references": [
            {
                "exclude": false,
                "record_id": "ba-01-N-4877"
            }
        ],
        "value": 1.7175982398952655e-06
    },
    "Ar40": {
        "error": 2.645357544269796e-06,
        "error_type": "",
        "fit": "previous",
        "references": [
            {
                "exclude": false,
                "record_id": "ba-01-N-4877"
            }
        ],
        "value": 6.98586978334773e-05
    }
}