{
    "Ar36": {
        "error": 2.1240595420091646,
        "error_type": "",
        "fit": "previous",
        "references": [
            {
                "exclude": false,
                "record_id": "ba-01-N-4954"
            }
        ],
        "value": 412.73510197004856
    },
    "Ar37": {
        "error": 6.113165701144896e-07,
        "error_type": "",
        "fit": "previous",
        "references": [
            {
                "exclude": false,
                "record_id": "ba-01-N-4954"
            }
        ],
        "value": 8.902265615597858e-06
    },
    "Ar38": {
        "error": 3.7233338503589625e-07,
        "error_type": "",
        "fit": "previous",
        "references": [
            {
                "exclude": false,
                "record_id": "ba-01-N-4954"
            }
        ],
        "value": 3.347426428313598e-06
    },
    "Ar39": {
        "error": 1.5513296393638205e-06,
        "error_type": "",
        "fit": "previous",
        "references": [
            {
                "exclude": false,
                "record_id": "ba-01-N-4954"
            }
        ],
        "value": 3.710038633496379e-06
    },
    "Ar40": {
        "error": 2.927623156887871e-06,
        "error_type": "",
        "fit": "previous",
        "references": [
            {
                "exclude": false,
                "record_id": "ba-01-N-4954"
            }
        ],
        "value": 5.157450877765799e-05
    }
}