{
    "Ar36": {
        "error": 0.6752964039734377,
        "error_type": "",
        "fit": "previous",
        "references": [
            {
                "exclude": false,
                "record_id": "ba-01-N-5113"
            }
        ],
        "value": 46.353910627199376
    },
    "Ar37": {
        "error": 2.191672627160385e-07,
        "error_type": "",
        "fit": "previous",
        "references": [
            {
                "exclude": false,
                "record_id": "ba-01-N-5113"
            }
        ],
        "value": 5.186785229439226e-06
    },
    "Ar38": {
        "error": 3.652838146016641e-07,
        "error_type": "",
        "fit": "previous",
        "references": [
            {
                "exclude": false,
                "record_id": "ba-01-N-5113"
            }
        ],
        "value": 4.0852259697510015e-07
    },
    "Ar39": {
        "error": 3.654348250395639e-07,
        "error_type": "",
        "fit": "previous",
        "references": [
            {
                "exclude": false,
                "record_id": "ba-01-N-5113"
            }
        ],
        "value": 2.2888976068938716e-07
    },
    "Ar40": {
        "error": 1.3394069443397301e-06,
        "error_type": "",
        "fit": "previous",
        "references": [
            {
                "exclude": false,
                "record_id": "ba-01-N-5113"
            }
        ],
        "value": 2.63599888166007e-05
    }
}