{
    "Ar36": {
        "error": 1.1161755333761414,
        "error_type": "",
        "fit": "previous",
        "references": [
            {
                "exclude": false,
                "record_id": "ba-01-N-5254"
            }
        ],
        "value": 26.67202116350447
    },
    "Ar37": {
        "error": 3.4279641256294244,
        "error_type": "",
        "fit": "previous",
        "references": [
            {
                "exclude": false,
                "record_id": "ba-01-N-5254"
            }
        ],
        "value": 140.34734738185725
    },
    "Ar38": {
        "error": 2.9505634040422115,
        "error_type": "",
        "fit": "previous",
        "references": [
            {
                "exclude": false,
                "record_id": "ba-01-N-5254"
            }
        ],
        "value": 190.40835953513107
    },
    "Ar39": {
        "error": 0.7431955132455265,
        "error_type": "",
        "fit": "previous",
        "references": [
            {
                "exclude": false,
                "record_id": "ba-01-N-5254"
            }
        ],
        "value": 27.35741952530138
    },
    "Ar40": {
        "error": 142.03650989955938,
        "error_type": "",
        "fit": "previous",
        "references": [
            {
                "exclude": false,
                "record_id": "ba-01-N-5254"
            }
        ],
        "value": 4807.361647205899
    }
}